Metadata-Version: 2.1
Name: bigzenodo
Version: 0.1.2
Summary: A tool for doing big uploads to Zenodo
Home-page: http://github.com/jakelever/bigzenodo
Author: Jake Lever
Author-email: jake.lever@gmail.com
License: MIT
Platform: UNKNOWN
Classifier: Intended Audience :: Science/Research
Classifier: License :: OSI Approved :: MIT License
Classifier: Operating System :: Unix
Classifier: Programming Language :: Python :: 3.6
Classifier: Topic :: Scientific/Engineering
License-File: LICENSE
